<?xml version="1.0" encoding="UTF-8"?>
<objects serializationModel="Studio.02.01.00">
	<object class="AudioFile" id="{c56c7afe-c9db-4eb5-a5cf-7f65133ee50d}">
		<property name="assetPath">
			<value>Portal.wav</value>
		</property>
		<property name="isStreaming">
			<value>true</value>
		</property>
		<property name="frequencyInKHz">
			<value>44.0999985</value>
		</property>
		<property name="channelCount">
			<value>2</value>
		</property>
		<property name="length">
			<value>28.392675736961451</value>
		</property>
		<relationship name="masterAssetFolder">
			<destination>{e20ea6a2-50c6-4bff-95e5-dcd4a6c89afa}</destination>
		</relationship>
	</object>
</objects>
